{
    "backend": "flask",
    "db_name": "",
    "db_pass": "",
    "db_type": "mysql",
    "db_user": "",
    "dbms": "1",
    "description": "generated product",
    "design": "atlantis-dark",
    "docker": "0",
    "err_code": 0,
    "frontend": "",
    "heroku": "0",
    "pattern": "mvc",
    "pro": "0",
    "task_id": "fd032938-4ec7-4744-9ee2-64ba411c50e0",
    "task_info": "Upload Sources [0%] - 512 files",
    "task_output": "fd032938-4ec7-4744-9ee2-64ba411c50e0.zip",
    "task_result": "SUCCESS",
    "task_state": "RUNNING",
    "task_ts_end": "2024-11-12-22-02-59",
    "task_ts_start": "2024-11-12-22-02-56"
}